README.md
setup.py
NlpToolkit_UniversalDependencyParser_Cy.egg-info/PKG-INFO
NlpToolkit_UniversalDependencyParser_Cy.egg-info/SOURCES.txt
NlpToolkit_UniversalDependencyParser_Cy.egg-info/dependency_links.txt
NlpToolkit_UniversalDependencyParser_Cy.egg-info/requires.txt
NlpToolkit_UniversalDependencyParser_Cy.egg-info/top_level.txt
Parser/__init__.py
Parser/TransitionBasedParser/Agenda.c
Parser/TransitionBasedParser/Agenda.pxd
Parser/TransitionBasedParser/Agenda.pyx
Parser/TransitionBasedParser/ArcEagerInstanceGenerator.c
Parser/TransitionBasedParser/ArcEagerInstanceGenerator.pxd
Parser/TransitionBasedParser/ArcEagerInstanceGenerator.pyx
Parser/TransitionBasedParser/ArcEagerOracle.c
Parser/TransitionBasedParser/ArcEagerOracle.pxd
Parser/TransitionBasedParser/ArcEagerOracle.pyx
Parser/TransitionBasedParser/ArcEagerTransitionParser.c
Parser/TransitionBasedParser/ArcEagerTransitionParser.pxd
Parser/TransitionBasedParser/ArcEagerTransitionParser.pyx
Parser/TransitionBasedParser/ArcStandardOracle.c
Parser/TransitionBasedParser/ArcStandardOracle.pxd
Parser/TransitionBasedParser/ArcStandardOracle.pyx
Parser/TransitionBasedParser/ArcStandardTransitionParser.c
Parser/TransitionBasedParser/ArcStandardTransitionParser.pxd
Parser/TransitionBasedParser/ArcStandardTransitionParser.pyx
Parser/TransitionBasedParser/Candidate.c
Parser/TransitionBasedParser/Candidate.pxd
Parser/TransitionBasedParser/Candidate.pyx
Parser/TransitionBasedParser/Command.py
Parser/TransitionBasedParser/Decision.c
Parser/TransitionBasedParser/Decision.pxd
Parser/TransitionBasedParser/Decision.pyx
Parser/TransitionBasedParser/InstanceGenerator.c
Parser/TransitionBasedParser/InstanceGenerator.pxd
Parser/TransitionBasedParser/InstanceGenerator.pyx
Parser/TransitionBasedParser/Oracle.c
Parser/TransitionBasedParser/Oracle.pxd
Parser/TransitionBasedParser/Oracle.pyx
Parser/TransitionBasedParser/RandomOracle.c
Parser/TransitionBasedParser/RandomOracle.pxd
Parser/TransitionBasedParser/RandomOracle.pyx
Parser/TransitionBasedParser/RandomScoringOracle.c
Parser/TransitionBasedParser/RandomScoringOracle.pxd
Parser/TransitionBasedParser/RandomScoringOracle.pyx
Parser/TransitionBasedParser/ScoringOracle.c
Parser/TransitionBasedParser/ScoringOracle.pxd
Parser/TransitionBasedParser/ScoringOracle.pyx
nlptoolkit_universaldependencyparser_cy.egg-info/PKG-INFO
nlptoolkit_universaldependencyparser_cy.egg-info/SOURCES.txt
nlptoolkit_universaldependencyparser_cy.egg-info/dependency_links.txt
nlptoolkit_universaldependencyparser_cy.egg-info/requires.txt
nlptoolkit_universaldependencyparser_cy.egg-info/top_level.txt